scenariogeneration/__init__.py
scenariogeneration/esmini_runner.py
scenariogeneration/helpers.py
scenariogeneration/scenario_generator.py
scenariogeneration/xodr/__init__.py
scenariogeneration/xodr/elevation.py
scenariogeneration/xodr/enumerations.py
scenariogeneration/xodr/exceptions.py
scenariogeneration/xodr/generators.py
scenariogeneration/xodr/geometry.py
scenariogeneration/xodr/junction_creator.py
scenariogeneration/xodr/lane.py
scenariogeneration/xodr/lane_def.py
scenariogeneration/xodr/links.py
scenariogeneration/xodr/opendrive.py
scenariogeneration/xodr/signals_objects.py
scenariogeneration/xodr/utils.py
scenariogeneration/xosc/__init__.py
scenariogeneration/xosc/actions.py
scenariogeneration/xosc/entities.py
scenariogeneration/xosc/enumerations.py
scenariogeneration/xosc/exceptions.py
scenariogeneration/xosc/parameters.py
scenariogeneration/xosc/position.py
scenariogeneration/xosc/scenario.py
scenariogeneration/xosc/storyboard.py
scenariogeneration/xosc/triggers.py
scenariogeneration/xosc/utils.py
scenariogeneration/xosc/xosc_reader.py
schemas/OpenSCENARIO_1_0.xsd
schemas/OpenSCENARIO_1_1.xsd
schemas/OpenSCENARIO_1_2.xsd
schemas/OpenSCENARIO_1_3_1.xsd
schemas/opendrive_17_core.xsd
schemas/opendrive_17_junction.xsd
schemas/opendrive_17_lane.xsd
schemas/opendrive_17_object.xsd
schemas/opendrive_17_railroad.xsd
schemas/opendrive_17_road.xsd
schemas/opendrive_17_signal.xsd
scenariogeneration-0.16.3.dist-info/AUTHORS
scenariogeneration-0.16.3.dist-info/LICENSE
scenariogeneration-0.16.3.dist-info/METADATA
scenariogeneration-0.16.3.dist-info/WHEEL
scenariogeneration-0.16.3.dist-info/top_level.txt
scenariogeneration-0.16.3.dist-info/RECORD
