Metadata-Version: 2.1
Name: scenariogeneration
Version: 0.16.3
Summary: Generation of OpenSCENARIO and OpenDRIVE xml files
Author-email: "M. Andersson, I. Natale, A. Tingberg" <andmika@gmail.com>
License: Mozilla Public License Version 2.0
Keywords: OpenDRIVE,OpenSCENARIO,xml
Classifier: Development Status :: 4 - Beta
Classifier: Programming Language :: Python :: 3
Classifier: Programming Language :: Python :: 3.9
Classifier: Programming Language :: Python :: 3.10
Classifier: Programming Language :: Python :: 3.11
Classifier: Programming Language :: Python :: 3.12
Classifier: License :: OSI Approved :: Mozilla Public License 2.0 (MPL 2.0)
Classifier: Operating System :: OS Independent
Requires-Python: >=3.9
License-File: LICENSE
License-File: AUTHORS
Requires-Dist: numpy
Requires-Dist: scipy
Requires-Dist: pyclothoids
Requires-Dist: xmlschema!=4.0.0,!=4.0.1,>=3.3.1
Requires-Dist: lxml
